testmodule.py
testsublib/__init__.py
testsublib/submodule.py
python_learning_demopackage-1.0.0.dist-info/LICENSE.txt
python_learning_demopackage-1.0.0.dist-info/METADATA
python_learning_demopackage-1.0.0.dist-info/WHEEL
python_learning_demopackage-1.0.0.dist-info/top_level.txt
python_learning_demopackage-1.0.0.dist-info/RECORD
