Metadata-Version: 2.1
Name: python-learning-demopackage
Version: 1.0.0
Summary: a demo package developed for python study
Home-page: https://www.baidu.com
Author: ahoo
Author-email: ahoo@gmail.com
License: MIT
License-File: LICENSE.txt
